deepseek_ocr/__init__.py
deepseek_ocr/__main__.py
deepseek_ocr/cli.py
deepseek_ocr/config.py
deepseek_ocr/model.py
deepseek_ocr/processor.py
deepseek_ocr/utils.py
deepseek_ocr_cli-0.3.1.dist-info/LICENSE
deepseek_ocr_cli-0.3.1.dist-info/METADATA
deepseek_ocr_cli-0.3.1.dist-info/WHEEL
deepseek_ocr_cli-0.3.1.dist-info/entry_points.txt
deepseek_ocr_cli-0.3.1.dist-info/RECORD
