Metadata-Version: 2.3
Name: deepseek-ocr-cli
Version: 0.3.1
Summary: CLI tool for OCR using DeepSeek-OCR model via Ollama
License: MIT
Keywords: ocr,deepseek,cli,pdf,document-processing,ollama
Author: Ruben Fernandez Fuertes
Author-email: fernandezfuertesruben@gmail.com
Requires-Python: >=3.10,<4.0
Classifier: Development Status :: 4 - Beta
Classifier: Intended Audience :: Developers
Classifier: Intended Audience :: Science/Research
Classifier: License :: OSI Approved :: MIT License
Classifier: Operating System :: OS Independent
Classifier: Programming Language :: Python :: 3
Classifier: Programming Language :: Python :: 3.10
Classifier: Programming Language :: Python :: 3.11
Classifier: Programming Language :: Python :: 3.12
Classifier: Programming Language :: Python :: 3.13
Classifier: Topic :: Scientific/Engineering :: Artificial Intelligence
Classifier: Topic :: Text Processing :: General
Requires-Dist: click (>=8.1.7,<9.0.0)
Requires-Dist: pillow (>=11.0.0,<12.0.0)
Requires-Dist: pydantic (>=2.10.0,<3.0.0)
Requires-Dist: pydantic-settings (>=2.7.0,<3.0.0)
Requires-Dist: pymupdf (>=1.25.1,<2.0.0)
Requires-Dist: python-dotenv (>=1.0.0,<2.0.0)
Requires-Dist: requests (>=2.31.0,<3.0.0)
Requires-Dist: rich (>=13.9.4,<14.0.0)
Requires-Dist: tqdm (>=4.67.0,<5.0.0)
Project-URL: Homepage, https://github.com/r-uben/deepseek-ocr-cli
Project-URL: Repository, https://github.com/r-uben/deepseek-ocr-cli
